auris/__init__.py
auris-0.0.1.dist-info/LICENSE
auris-0.0.1.dist-info/METADATA
auris-0.0.1.dist-info/WHEEL
auris-0.0.1.dist-info/top_level.txt
auris-0.0.1.dist-info/RECORD
