Metadata-Version: 2.1
Name: auris
Version: 0.0.1
Summary: Audio Understanding for Resource-constrained Intelligent Systems
Author-email: "Karol J. Piczak" <karol@piczak.com>
License: MIT
Project-URL: Homepage, https://github.com/karolpiczak/auris
Project-URL: Bug Tracker, https://github.com/karolpiczak/auris/issues
Keywords: audio,embedded,neural networks,edge ai,microcontrollers
Platform: any
Classifier: Programming Language :: Python :: 3.13
Classifier: License :: OSI Approved :: MIT License
Classifier: Operating System :: OS Independent
Classifier: Development Status :: 2 - Pre-Alpha
Classifier: Typing :: Typed
Classifier: Topic :: Multimedia :: Sound/Audio :: Analysis
Classifier: Topic :: Scientific/Engineering :: Artificial Intelligence
Classifier: Topic :: Software Development :: Embedded Systems
Requires-Python: >=3.13
License-File: LICENSE
Provides-Extra: dev
Requires-Dist: setuptools>=67.2; extra == "dev"
Requires-Dist: setuptools-scm[toml]>=7.1; extra == "dev"
Requires-Dist: wheel; extra == "dev"
